pyatspi/Accessibility.py
pyatspi/__init__.py
pyatspi/action.py
pyatspi/appevent.py
pyatspi/application.py
pyatspi/atspienum.py
pyatspi/collection.py
pyatspi/component.py
pyatspi/constants.py
pyatspi/deviceevent.py
pyatspi/document.py
pyatspi/editabletext.py
pyatspi/hypertext.py
pyatspi/image.py
pyatspi/interface.py
pyatspi/registry.py
pyatspi/role.py
pyatspi/selection.py
pyatspi/state.py
pyatspi/table.py
pyatspi/tablecell.py
pyatspi/text.py
pyatspi/utils.py
pyatspi/value.py
python3_pyatspi-1.19.0.dist-info/METADATA
python3_pyatspi-1.19.0.dist-info/WHEEL
python3_pyatspi-1.19.0.dist-info/licenses/LICENSE
python3_pyatspi-1.19.0.dist-info/RECORD
