Metadata-Version: 2.1
Name: python3-pyatspi
Version: 1.19.0
Author-email: mikigo <huangmingqiang@uniontech.com>
License: GPL2.0
License-File: LICENSE
Requires-Python: >=3.6
